pi_mcp23017/__init__.py
pi_mcp23017/mcp23017.py
pi_mcp23017-1.0.0.dist-info/LICENSE
pi_mcp23017-1.0.0.dist-info/WHEEL
pi_mcp23017-1.0.0.dist-info/METADATA
pi_mcp23017-1.0.0.dist-info/RECORD
